pyDFTutils/__init__.py
pyDFTutils/abinit/DDB_reader.py
pyDFTutils/abinit/__init__.py
pyDFTutils/abinit/abihist_file.py
pyDFTutils/abinit/abinit.py
pyDFTutils/abinit/abinit_io.py
pyDFTutils/abinit/abinit_reader.py
pyDFTutils/abinit/dos.py
pyDFTutils/abinit/myabinit.py
pyDFTutils/abinit/myabinit_e.py
pyDFTutils/abinit/myabinit_vca.py
pyDFTutils/abinit/read_2DE.py
pyDFTutils/abipy/Perovskite.py
pyDFTutils/abipy/__init__.py
pyDFTutils/abipy/abi_poscar.py
pyDFTutils/abipy/flow.py
pyDFTutils/abipy/input_utils.py
pyDFTutils/abipy/pp_finder.py
pyDFTutils/abipy/test.py
pyDFTutils/ase_utils/__init__.py
pyDFTutils/ase_utils/ase_utils.py
pyDFTutils/ase_utils/frozenphonon.py
pyDFTutils/ase_utils/gen_pp.py
pyDFTutils/ase_utils/geometry.py
pyDFTutils/ase_utils/get_wyckoff.py
pyDFTutils/ase_utils/ioput.py
pyDFTutils/ase_utils/kpoints.py
pyDFTutils/ase_utils/map_atoms.py
pyDFTutils/ase_utils/mcif.py
pyDFTutils/ase_utils/refine.py
pyDFTutils/ase_utils/spacegroup.py
pyDFTutils/ase_utils/symbol.py
pyDFTutils/chgnet/__init__.py
pyDFTutils/chgnet/chgnet_ase.py
pyDFTutils/chgnet/tranin_chgnet.py
pyDFTutils/espresso/Pwscf.py
pyDFTutils/espresso/__init__.py
pyDFTutils/espresso/qe_pp_finder.py
pyDFTutils/math/__init__.py
pyDFTutils/math/peakdetect.py
pyDFTutils/multibinit/__init__.py
pyDFTutils/multibinit/mb_spinhist_parser.py
pyDFTutils/perovskite/__init__.py
pyDFTutils/perovskite/calc_many.py
pyDFTutils/perovskite/cubic_perovskite.py
pyDFTutils/perovskite/frozen_mode.py
pyDFTutils/perovskite/gen_111.py
pyDFTutils/perovskite/lattice_factory.py
pyDFTutils/perovskite/octahedra.py
pyDFTutils/perovskite/perovskite_mode.py
pyDFTutils/perovskite/plotphon.py
pyDFTutils/perovskite/tfactor.py
pyDFTutils/phonon/__init__.py
pyDFTutils/phonon/gen_structures_from_DDB.py
pyDFTutils/phonon/parser.py
pyDFTutils/phonon/plot_abinit_phonon.py
pyDFTutils/phonon/plot_phon_nc.py
pyDFTutils/phonon/plotddbband.py
pyDFTutils/phonon/plotphonopy.py
pyDFTutils/plot/__init__.py
pyDFTutils/plot/wannier_band_plot.py
pydftutils-0.2.8.dist-info/licenses/LICENSE
pydftutils-0.2.8.dist-info/METADATA
pydftutils-0.2.8.dist-info/WHEEL
pydftutils-0.2.8.dist-info/top_level.txt
pydftutils-0.2.8.dist-info/RECORD
